pycalcpad/PyCalcpadWrapper.py
pycalcpad/__init__.py
pycalcpad-0.0.3.dist-info/LICENSE
pycalcpad-0.0.3.dist-info/METADATA
pycalcpad-0.0.3.dist-info/WHEEL
pycalcpad-0.0.3.dist-info/top_level.txt
pycalcpad-0.0.3.dist-info/RECORD
